Workbook

Sheet 使用说明
A1: 投资收益概率分析模型 · 使用说明
A3: 如何使用
A4: 1. 本工作簿所有蓝色字体单元格均为可修改参数：价格、累积概率、回报倍数、配置比例等，改完其余各表自动重算。
A5: 2. 修改「参数输入」表中的概率后，「A公司分析」「B公司分析」「组合配置与结论」全部自动更新。
A6: 3. 概率统一采用累积概率口径：表示「期末价格 ≥ 该价位（或回报倍数 ≥ 该倍数）」的概率；区间概率由模型自动相邻相减得到。
A7: 4. 「组合配置与结论」表可选择风险偏好（稳健 / 平衡 / 进取，B4 单元格下拉选择），推荐比例由评分法「期望年化收益 − λ×年化波动率」自动计算（λ 系数可在 D/E 列调整）；A 公司实际配置默认自动跟随推荐，如需自定义可直接输入覆盖。
A9: 模型口径
A10: A公司（已上市）：现价 200 元，以 200 元建仓 100 万元（5,000 股），预测 2 年后股价分布；区间收益率按区间下限保守估计，即收益率 = 下限价 ÷ 200 − 1。
A11: B公司（Pre-IPO）：明年申报、后年上市、上市后锁定 1 年方可卖出（约 3 年后退出）；上市成功率 60%，不成功则退还本金并按每年 6% 利息补偿（利率可调、按退出期限复利），成功时按回报倍数分布计算。
A12: 组合结论综合「期望年化收益率对比 + 悲观情景底线测试」自动给出，并提示 B 公司的仓位纪律。
A14: 风险提示：所有概率均为预测假设，模型结果仅供决策参考，不构成投资建议。

Sheet 参数输入
A1: 参数输入（蓝色字体可修改，黑色与绿色为自动计算）
A3: 【A公司 · 已上市股票】
A4: 当前股价（元） | B4: 200 | C4: 买入价 = 建仓成本基准
A5: 投入本金（元） | B5: 1000000
A6: 持有股数（股） | B6: =B5/B4 -> 5000
A7: 预测期限（年） | B7: 2
A8: 目标价格（元） | B8: 累积概率（≥该价） | C8: 含义：两年后价格不低于左侧行价格的概率
A9: 200 | B9: 1
A10: 250 | B10: 0.95
A11: 300 | B11: 0.75
A12: 350 | B12: 0.5
A13: 400 | B13: 0.3
A14: 450 | B14: 0.2
A15: 500 | B15: 0.1
A16: 概率合计（应为100%） | B16: =SUM(B9:B15) -> 3.8
A18: 【B公司 · Pre-IPO股权投资】
A19: 上市成功概率 | B19: 0.6 | C19: 明年申报、后年上市
A20: 失败时年化补偿利率 | B20: 0.06 | C20: 上市不成功则退还本金，并按该年利率随退出期限复利计息
A21: 退出期限（年） | B21: 3 | C21: 申报1年 + 上市 + 锁定1年
A22: 回报倍数（倍） | B22: 累积概率（≥该倍数） | C22: 含义：上市成功、锁定期满时可卖价格不低于成本倍数的概率
A23: 3 | B23: 0.9
A24: 4 | B24: 0.7
A25: 5 | B25: 0.5
A26: 6 | B26: 0.4
A27: 7 | B27: 0.3
A28: 8 | B28: 0.2
A29: 概率合计（应为100%） | B29: =SUM(B23:B28) -> 3
A30: 未达3倍时的假设回报倍数 | B30: 1 | C30: 上市成功但回报不足3倍时，按该倍数（即接近保本）估计

Sheet A公司分析
A1: A公司收益分析（持有2年后的股价情景）
A3: 价格下限（元） | B3: 价格上限（元） | C3: 区间概率 | D3: 区间收益率 | E3: 期末价值（元） | F3: 概率加权价值（元）
A4: =参数输入!A9 -> 200 | B4: =参数输入!A10 -> 250 | C4: =参数输入!B9-参数输入!B10 -> 0.05 | D4: =A4/参数输入!B4-1 -> 0 | E4: =参数输入!B5*(1+D4) -> 1000000 | F4: =C4*E4 -> 50000
A5: =参数输入!A10 -> 250 | B5: =参数输入!A11 -> 300 | C5: =参数输入!B10-参数输入!B11 -> 0.2 | D5: =A5/参数输入!B4-1 -> 0.25 | E5: =参数输入!B5*(1+D5) -> 1250000 | F5: =C5*E5 -> 250000
A6: =参数输入!A11 -> 300 | B6: =参数输入!A12 -> 350 | C6: =参数输入!B11-参数输入!B12 -> 0.25 | D6: =A6/参数输入!B4-1 -> 0.5 | E6: =参数输入!B5*(1+D6) -> 1500000 | F6: =C6*E6 -> 375000
A7: =参数输入!A12 -> 350 | B7: =参数输入!A13 -> 400 | C7: =参数输入!B12-参数输入!B13 -> 0.2 | D7: =A7/参数输入!B4-1 -> 0.75 | E7: =参数输入!B5*(1+D7) -> 1750000 | F7: =C7*E7 -> 350000
A8: =参数输入!A13 -> 400 | B8: =参数输入!A14 -> 450 | C8: =参数输入!B13-参数输入!B14 -> 0.1 | D8: =A8/参数输入!B4-1 -> 1 | E8: =参数输入!B5*(1+D8) -> 2000000 | F8: =C8*E8 -> 200000
A9: =参数输入!A14 -> 450 | B9: =参数输入!A15 -> 500 | C9: =参数输入!B14-参数输入!B15 -> 0.1 | D9: =A9/参数输入!B4-1 -> 1.25 | E9: =参数输入!B5*(1+D9) -> 2250000 | F9: =C9*E9 -> 225000
A10: =参数输入!A15 -> 500 | B10: 500 以上 | C10: =参数输入!B15 -> 0.1 | D10: =A10/参数输入!B4-1 -> 1.5 | E10: =参数输入!B5*(1+D10) -> 2500000 | F10: =C10*E10 -> 250000
A11: 合计 | C11: =SUM(C4:C10) -> 1 | D11: 期望期末价值 → | F11: =SUM(F4:F10) -> 1700000
A13: 核心结果
A14: 期望期末价值（元） | B14: =F11 -> 1700000
A15: 期望总收益率 | B15: =B14/参数输入!B5-1 -> 0.7
A16: 期望年化收益率 | B16: =(B14/参数输入!B5)^(1/参数输入!B7)-1 -> 0.30384048
A17: 中位数价格（50%概率达到） | B17: =INDEX(参数输入!A9:A15,MATCH(0.5,参数输入!B9:B15,-1)) -> 350
A18: 最可能价格区间（元） | B18: =INDEX(A4:A10,MATCH(MAX(C4:C10),C4:C10,0))&" - "&INDEX(B4:B10,MATCH(MAX(C4:C10),C4:C10,0)) -> 300 - 350
A19: 跌破买入价的概率 | B19: =1-参数输入!B9 -> 0 | C19: 按当前假设，最低价即买入价200元
A21: 年化波动率（风险度量） | B21: =SQRT(SUMPRODUCT(C4:C10,(D4:D10-B15)^2))/SQRT(参数输入!B7) -> 0.29895652 | C21: 各区间收益率的标准差折算为年化，供组合评分使用

Sheet B公司分析
A1: B公司收益分析（Pre-IPO · 约3年后退出）
A3: 回报倍数区间（上市成功时） | B3: 区间概率 | C3: 代表倍数 | D3: 概率加权回报
A4: 低于3倍（按假设倍数） | B4: =1-参数输入!B23 -> 0.1 | C4: =参数输入!B30 -> 1 | D4: =B4*C4 -> 0.1
A5: 3 - 4 倍 | B5: =参数输入!B23-参数输入!B24 -> 0.2 | C5: =(参数输入!A23+参数输入!A24)/2 -> 3.5 | D5: =B5*C5 -> 0.7
A6: 4 - 5 倍 | B6: =参数输入!B24-参数输入!B25 -> 0.2 | C6: =(参数输入!A24+参数输入!A25)/2 -> 4.5 | D6: =B6*C6 -> 0.9
A7: 5 - 6 倍 | B7: =参数输入!B25-参数输入!B26 -> 0.1 | C7: =(参数输入!A25+参数输入!A26)/2 -> 5.5 | D7: =B7*C7 -> 0.55
A8: 6 - 7 倍 | B8: =参数输入!B26-参数输入!B27 -> 0.1 | C8: =(参数输入!A26+参数输入!A27)/2 -> 6.5 | D8: =B8*C8 -> 0.65
A9: 7 - 8 倍 | B9: =参数输入!B27-参数输入!B28 -> 0.1 | C9: =(参数输入!A27+参数输入!A28)/2 -> 7.5 | D9: =B9*C9 -> 0.75
A10: 8 倍及以上 | B10: =参数输入!B28 -> 0.2 | C10: =参数输入!A28 -> 8 | D10: =B10*C10 -> 1.6
A11: 合计 | B11: =SUM(B4:B10) -> 1 | C11: 期望倍数 → | D11: =SUM(D4:D10) -> 5.25
A13: 核心结果
A14: 上市成功时期望回报倍数 | B14: =D11 -> 5.25
A15: 综合期望回报倍数（含失败情形） | B15: =参数输入!B19*B14+(1-参数输入!B19)*((1+参数输入!B20)^参数输入!B21) -> 3.6264064
A16: 综合期望总收益率 | B16: =B15-1 -> 2.6264064
A17: 综合期望年化收益率 | B17: =B15^(1/参数输入!B21)-1 -> 0.53635705
A18: 上市失败概率 | B18: =1-参数输入!B19 -> 0.4
A19: 上市失败时期望回收金额（元） | B19: =((1+参数输入!B20)^参数输入!B21)*参数输入!B5 -> 1191016 | C19: 指每100万投入的回收额（本金+利息）
A20: 最可能回报区间 | B20: =INDEX(A4:A10,MATCH(MAX(B4:B10),B4:B10,0))&"（区间概率 "&TEXT(MAX(B4:B10),"0.0%")&"）" -> 3 - 4 倍（区间概率 20.0%）
A21: 失败时本金回收倍数（含补偿利息） | B21: =(1+参数输入!B20)^参数输入!B21 -> 1.191016 | C21: =（1+年利率）^退出期限，复利
A23: 联合分布（上市失败 + 上市成功，用于风险度量）
A24: 上市失败（退还本金+利息） | B24: =1-参数输入!B19 -> 0.4 | C24: =B21 -> 1.191016
A25: 低于3倍（上市成功） | B25: =参数输入!B19*B4 -> 0.06 | C25: =C4 -> 1
A26: 3-4倍（上市成功） | B26: =参数输入!B19*B5 -> 0.12 | C26: =C5 -> 3.5
A27: 4-5倍（上市成功） | B27: =参数输入!B19*B6 -> 0.12 | C27: =C6 -> 4.5
A28: 5-6倍（上市成功） | B28: =参数输入!B19*B7 -> 0.06 | C28: =C7 -> 5.5
A29: 6-7倍（上市成功） | B29: =参数输入!B19*B8 -> 0.06 | C29: =C8 -> 6.5
A30: 7-8倍（上市成功） | B30: =参数输入!B19*B9 -> 0.06 | C30: =C9 -> 7.5
A31: 8倍及以上（上市成功） | B31: =参数输入!B19*B10 -> 0.12 | C31: =C10 -> 8
A32: 年化波动率（风险度量） | B32: =SQRT(SUMPRODUCT(B24:B31,(C24:C31-B15)^2))/SQRT(参数输入!B21) -> 1.5035053 | C32: 含上市失败情形的整体标准差折算为年化

Sheet 组合配置与结论
A1: 组合配置与自动结论（总本金取自参数输入表）
A3: 第一步：设置风险偏好与配置（推荐比例由评分法自动计算）
A4: 风险偏好（稳健 / 平衡 / 进取） | B4: 平衡 | C4: 点击B4下拉选择；右侧D/E列可调风险厌恶系数λ | D4: λ-稳健 | E4: 0.6
A5: A公司推荐配置比例（评分法） | B5: =IF((A公司分析!B16-E7*A公司分析!B21)+(B公司分析!B17-E7*B公司分析!B32)<=0,0.9,MAX(0.1,MIN(0.9,(A公司分析!B16-E7*A公司分析!B21)/((A公司分析!B16-E7*A公司分析!B21)+(B公司分析!B17-E7*B公司分析!B32))))) -> 0.71513472 | C5: 评分 = 期望年化收益 − λ×年化波动率 | D5: λ-平衡 | E5: 0.3
A6: B公司推荐配置比例 | B6: =1-B5 -> 0.28486528 | C6: = 1 − A公司推荐比例（限10%~90%） | D6: λ-进取 | E6: 0.1
A7: A公司实际配置比例（自动跟随推荐） | B7: =B5 -> 0.71513472 | C7: 如需手动覆盖，直接在本格输入比例即可 | D7: 当前λ | E7: =IF(B4="稳健",E4,IF(B4="进取",E6,E5)) -> 0.3
A8: B公司实际配置比例 | B8: =1-B7 -> 0.28486528
A9: A公司投入金额（元） | B9: =参数输入!B5*B7 -> 715134.72
A10: B公司投入金额（元） | B10: =参数输入!B5*B8 -> 284865.28
A12: 第二步：组合期望收益
A13: A部分期望期末价值（2年后） | B13: =B9*(1+A公司分析!B15) -> 1215729
A14: B部分期望期末价值（3年后） | B14: =B10*B公司分析!B15 -> 1033037.3
A15: 组合期望期末价值（元） | B15: =B13+B14 -> 2248766.3
A16: 组合期望总收益率 | B16: =B15/参数输入!B5-1 -> 1.2487663
A17: 加权平均期望年化收益率 | B17: =B7*A公司分析!B16+B8*B公司分析!B17 -> 0.37007638
A19: 第三步：情景分析
A20: 情景 | B20: A公司价格 | C20: A部分期末（元） | D20: B公司倍数 | E20: B部分期末（元） | F20: 组合期末（元） | G20: 组合总收益率
A21: 悲观（A跌至250元 / B失败退本息） | B21: =参数输入!A10 -> 250 | C21: =$B$9*(B21/参数输入!B4) -> 893918.4 | D21: =(1+参数输入!B20)^参数输入!B21 -> 1.191016 | E21: =$B$10*D21 -> 339279.1 | F21: =C21+E21 -> 1233197.5 | G21: =F21/参数输入!B5-1 -> 0.23319751
A22: 中性（A达中位数350元 / B达4倍） | B22: =参数输入!A12 -> 350 | C22: =$B$9*(B22/参数输入!B4) -> 1251485.8 | D22: =参数输入!A24 -> 4 | E22: =$B$10*D22 -> 1139461.1 | F22: =C22+E22 -> 2390946.9 | G22: =F22/参数输入!B5-1 -> 1.3909469
A23: 乐观（A达450元 / B达6倍） | B23: =参数输入!A14 -> 450 | C23: =$B$9*(B23/参数输入!B4) -> 1609053.1 | D23: =参数输入!A26 -> 6 | E23: =$B$10*D23 -> 1709191.7 | F23: =C23+E23 -> 3318244.8 | G23: =F23/参数输入!B5-1 -> 2.3182448
A25: 自动结论（随上方参数实时更新）
A26: ="1. 收益对比：A公司期望年化 "&TEXT(A公司分析!B16,"0.0%")&"，B公司综合期望年化 "&TEXT(B公司分析!B17,"0.0%")&IF(A公司分析!B16>=B公司分析!B17,"，A公司占优但天花板有限；","，B公司弹性更高但伴随失败风险；")&"B公司综合期望倍数 "&TEXT(B公司分析!B15,"0.00")&" 倍。" -> 1. 收益对比：A公司期望年化 30.4%，B公司综合期望年化 53.6%，B公司弹性更高但伴随失败风险；B公司综合期望倍数 3.63 倍。
A27: ="2. 配置建议（"&B4&"型，λ="&TEXT(E7,"0.0%")&"）：按评分「期望年化收益 − λ×年化波动率」自动计算，推荐 A "&TEXT(B5,"0%")&" / B "&TEXT(B6,"0%")&"；当前实际配置 A "&TEXT(B7,"0%")&" / B "&TEXT(B8,"0%")&IF(B7=B5,"，与推荐一致。","，已手动覆盖推荐。") -> 2. 配置建议（平衡型，λ=30.0%）：按评分「期望年化收益 − λ×年化波动率」自动计算，推荐 A 72% / B 28%；当前实际配置 A 72% / B 28%，与推荐一致。
A28: ="3. 底线测试：若A仅跌至 "&TEXT(参数输入!A10,"0")&" 元且B上市失败（退还本金+补偿利息），组合期末约 "&TEXT(F21,"#,##0")&" 元（总收益率 "&TEXT(G21,"0.0%")&"）；B失败情形已有保本+利息保障，回撤主要来自A的股价假设。" -> 3. 底线测试：若A仅跌至 250 元且B上市失败（退还本金+补偿利息），组合期末约 1,233,198 元（总收益率 23.3%）；B失败情形已有保本+利息保障，回撤主要来自A的股价假设。
A29: ="4. 乐观空间：A达 "&TEXT(参数输入!A14,"0")&" 元、B达 "&TEXT(参数输入!A26,"0")&" 倍时，组合期末约 "&TEXT(F23,"#,##0")&" 元（总收益率 "&TEXT(G23,"0.0%")&"）。" -> 4. 乐观空间：A达 450 元、B达 6 倍时，组合期末约 3,318,245 元（总收益率 231.8%）。
A30: ="5. 结论：评分法下推荐 A "&TEXT(B5,"0%")&" / B "&TEXT(B6,"0%")&"。B公司年化波动率约 "&TEXT(B公司分析!B32,"0.0%")&"，为A公司（"&TEXT(A公司分析!B21,"0.0%")&"）的 "&TEXT(IF(A公司分析!B21=0,0,B公司分析!B32/A公司分析!B21),"0.0")&" 倍，虽期望年化更高（"&TEXT(B公司分析!B17,"0.0%")&" vs "&TEXT(A公司分析!B16,"0.0%")&"），仍需以评分和自身流动性需求为准；B公司基础数据（成功率、倍数、失败利息）任一变化，推荐比例自动重算。" -> 5. 结论：评分法下推荐 A 72% / B 28%。B公司年化波动率约 150.4%，为A公司（29.9%）的 5.0 倍，虽期望年化更高（53.6% vs 30.4%），仍需以评分和自身流动性需求为准；B公司基础数据（成功率、倍数、失败利息）任一变化，推荐比例自动重算。
A31: 提示：修改任意蓝色参数后本表结论自动更新；概率为预测假设，仅供决策参考，不构成投资建议。
